mydata/__init__.py
mydata/__main__.py
mydata/client.py
mydata/ingest_xsd.py
mydata/models_1_0_10.py
mydata/models_v1_0_7.py
mydata/models_v1_0_8.py
mydata/models_v1_0_9.py
mydata_client-0.2.1.dist-info/LICENSE
mydata_client-0.2.1.dist-info/METADATA
mydata_client-0.2.1.dist-info/NOTICE.md
mydata_client-0.2.1.dist-info/WHEEL
mydata_client-0.2.1.dist-info/entry_points.txt
mydata_client-0.2.1.dist-info/RECORD
