Metadata-Version: 2.3
Name: mydata-client
Version: 0.2.1
Summary: Python interface for IARP's myDATA service
License: MPL-2.0
Author: Alex Pyrgiotis
Author-email: apyrgio@gmail.com
Requires-Python: >=3.9,<4.0
Classifier: License :: OSI Approved
Classifier: Programming Language :: Python :: 3
Classifier: Programming Language :: Python :: 3.9
Classifier: Programming Language :: Python :: 3.10
Classifier: Programming Language :: Python :: 3.11
Classifier: Programming Language :: Python :: 3.12
Classifier: Programming Language :: Python :: 3.13
Requires-Dist: click (>=8.1.7,<9.0.0)
Requires-Dist: qrcode (>=7.4.2,<8.0.0)
Requires-Dist: requests (>=2.31.0,<3.0.0)
Requires-Dist: rich (>=13.7.0,<14.0.0)
Requires-Dist: xsdata (>=24.1,<25.0)
